{
	"bricks": 
	[
		{ "size_x": 90, "size_y": 40, "position_x": -500, "position_y": -300, "texture_id": 5 },
		{ "size_x": 90, "size_y": 40, "position_x": -400, "position_y": -300, "texture_id": 5 },
		{ "size_x": 90, "size_y": 40, "position_x": -300, "position_y": -300, "texture_id": 5 },
		{ "size_x": 90, "size_y": 40, "position_x": -200, "position_y": -300, "texture_id": 5 },
		{ "size_x": 90, "size_y": 40, "position_x": -100, "position_y": -300, "texture_id": 5 },
		{ "size_x": 90, "size_y": 40, "position_x": 0, "position_y": -300, "texture_id": 5 },
		{ "size_x": 90, "size_y": 40, "position_x": 100, "position_y": -300, "texture_id": 5 },
		{ "size_x": 90, "size_y": 40, "position_x": 200, "position_y": -300, "texture_id": 5 },
		{ "size_x": 90, "size_y": 40, "position_x": 300, "position_y": -300, "texture_id": 5 },
		{ "size_x": 90, "size_y": 40, "position_x": 400, "position_y": -300, "texture_id": 5 },
		{ "size_x": 90, "size_y": 40, "position_x": 500, "position_y": -300, "texture_id": 5 },

		{ "size_x": 90, "size_y": 40, "position_x": -500, "position_y": -250, "texture_id": 4 },
		{ "size_x": 90, "size_y": 40, "position_x": -400, "position_y": -250, "texture_id": 4 },
		{ "size_x": 90, "size_y": 40, "position_x": -300, "position_y": -250, "texture_id": 4 },
		{ "size_x": 90, "size_y": 40, "position_x": -200, "position_y": -250, "texture_id": 4 },
		{ "size_x": 90, "size_y": 40, "position_x": -100, "position_y": -250, "texture_id": 4 },
		{ "size_x": 90, "size_y": 40, "position_x": 0, "position_y": -250, "texture_id": 4 },
		{ "size_x": 90, "size_y": 40, "position_x": 100, "position_y": -250, "texture_id": 4 },
		{ "size_x": 90, "size_y": 40, "position_x": 200, "position_y": -250, "texture_id": 4 },
		{ "size_x": 90, "size_y": 40, "position_x": 300, "position_y": -250, "texture_id": 4 },
		{ "size_x": 90, "size_y": 40, "position_x": 400, "position_y": -250, "texture_id": 4 },
		{ "size_x": 90, "size_y": 40, "position_x": 500, "position_y": -250, "texture_id": 4 },

		{ "size_x": 90, "size_y": 40, "position_x": -500, "position_y": -200, "texture_id": 3 },
		{ "size_x": 90, "size_y": 40, "position_x": -400, "position_y": -200, "texture_id": 3 },
		{ "size_x": 90, "size_y": 40, "position_x": -300, "position_y": -200, "texture_id": 3 },
		{ "size_x": 90, "size_y": 40, "position_x": -200, "position_y": -200, "texture_id": 3 },
		{ "size_x": 90, "size_y": 40, "position_x": -100, "position_y": -200, "texture_id": 3 },
		{ "size_x": 90, "size_y": 40, "position_x": 0, "position_y": -200, "texture_id": 3 },
		{ "size_x": 90, "size_y": 40, "position_x": 100, "position_y": -200, "texture_id": 3 },
		{ "size_x": 90, "size_y": 40, "position_x": 200, "position_y": -200, "texture_id": 3 },
		{ "size_x": 90, "size_y": 40, "position_x": 300, "position_y": -200, "texture_id": 3 },
		{ "size_x": 90, "size_y": 40, "position_x": 400, "position_y": -200, "texture_id": 3 },
		{ "size_x": 90, "size_y": 40, "position_x": 500, "position_y": -200, "texture_id": 3 },

		{ "size_x": 90, "size_y": 40, "position_x": -500, "position_y": -150, "texture_id": 2 },
		{ "size_x": 90, "size_y": 40, "position_x": -400, "position_y": -150, "texture_id": 2 },
		{ "size_x": 90, "size_y": 40, "position_x": -300, "position_y": -150, "texture_id": 2 },
		{ "size_x": 90, "size_y": 40, "position_x": -200, "position_y": -150, "texture_id": 2 },
		{ "size_x": 90, "size_y": 40, "position_x": -100, "position_y": -150, "texture_id": 2 },
		{ "size_x": 90, "size_y": 40, "position_x": 0, "position_y": -150, "texture_id": 2 },
		{ "size_x": 90, "size_y": 40, "position_x": 100, "position_y": -150, "texture_id": 2 },
		{ "size_x": 90, "size_y": 40, "position_x": 200, "position_y": -150, "texture_id": 2 },
		{ "size_x": 90, "size_y": 40, "position_x": 300, "position_y": -150, "texture_id": 2 },
		{ "size_x": 90, "size_y": 40, "position_x": 400, "position_y": -150, "texture_id": 2 },
		{ "size_x": 90, "size_y": 40, "position_x": 500, "position_y": -150, "texture_id": 2 },

		{ "size_x": 90, "size_y": 40, "position_x": -500, "position_y": -100, "texture_id": 1 },
		{ "size_x": 90, "size_y": 40, "position_x": -400, "position_y": -100, "texture_id": 1 },
		{ "size_x": 90, "size_y": 40, "position_x": -300, "position_y": -100, "texture_id": 1 },
		{ "size_x": 90, "size_y": 40, "position_x": -200, "position_y": -100, "texture_id": 1 },
		{ "size_x": 90, "size_y": 40, "position_x": -100, "position_y": -100, "texture_id": 1 },
		{ "size_x": 90, "size_y": 40, "position_x": 0, "position_y": -100, "texture_id": 1 },
		{ "size_x": 90, "size_y": 40, "position_x": 100, "position_y": -100, "texture_id": 1 },
		{ "size_x": 90, "size_y": 40, "position_x": 200, "position_y": -100, "texture_id": 1 },
		{ "size_x": 90, "size_y": 40, "position_x": 300, "position_y": -100, "texture_id": 1 },
		{ "size_x": 90, "size_y": 40, "position_x": 400, "position_y": -100, "texture_id": 1 },
		{ "size_x": 90, "size_y": 40, "position_x": 500, "position_y": -100, "texture_id": 1 },
	
	  { "size_x": 90, "size_y": 40, "position_x": -500, "position_y": -50, "texture_id": 0 },
		{ "size_x": 90, "size_y": 40, "position_x": -400, "position_y": -50, "texture_id": 0 },
		{ "size_x": 90, "size_y": 40, "position_x": -300, "position_y": -50, "texture_id": 0 },
		{ "size_x": 90, "size_y": 40, "position_x": -200, "position_y": -50, "texture_id": 0 },
		{ "size_x": 90, "size_y": 40, "position_x": -100, "position_y": -50, "texture_id": 0 },
		{ "size_x": 90, "size_y": 40, "position_x": 0, "position_y": -50, "texture_id": 0 },
		{ "size_x": 90, "size_y": 40, "position_x": 100, "position_y": -50, "texture_id": 0 },
		{ "size_x": 90, "size_y": 40, "position_x": 200, "position_y": -50, "texture_id": 0 },
		{ "size_x": 90, "size_y": 40, "position_x": 300, "position_y": -50, "texture_id": 0 },
		{ "size_x": 90, "size_y": 40, "position_x": 400, "position_y": -50, "texture_id": 0 },
		{ "size_x": 90, "size_y": 40, "position_x": 500, "position_y": -50, "texture_id": 0 },
	
	  { "size_x": 90, "size_y": 40, "position_x": -500, "position_y": 0, "texture_id": 0 },
		{ "size_x": 90, "size_y": 40, "position_x": -400, "position_y": 0, "texture_id": 0 },
		{ "size_x": 90, "size_y": 40, "position_x": -300, "position_y": 0, "texture_id": 0 },
		{ "size_x": 90, "size_y": 40, "position_x": -200, "position_y": 0, "texture_id": 0 },
		{ "size_x": 90, "size_y": 40, "position_x": -100, "position_y": 0, "texture_id": 0 },
		{ "size_x": 90, "size_y": 40, "position_x": 0, "position_y": 0, "texture_id": 0 },
		{ "size_x": 90, "size_y": 40, "position_x": 100, "position_y": 0, "texture_id": 0 },
		{ "size_x": 90, "size_y": 40, "position_x": 200, "position_y": 0, "texture_id": 0 },
		{ "size_x": 90, "size_y": 40, "position_x": 300, "position_y": 0, "texture_id": 0 },
		{ "size_x": 90, "size_y": 40, "position_x": 400, "position_y": 0, "texture_id": 0 },
		{ "size_x": 90, "size_y": 40, "position_x": 500, "position_y": 0, "texture_id": 0 }
  ]
}